DESCRIPTION.rst
LICENSE
MANIFEST.in
README.rst
setup.py
FUCHS/FUCHS.py
FUCHS/__init__.py
FUCHS/detect_skipped_exons.py
FUCHS/detect_splicing_variants.py
FUCHS/extract_reads.py
FUCHS/get_coverage_profile.py
FUCHS/get_mate_information.py
FUCHS/get_readnames_from_DCC.py
FUCHS/guided_denovo_circle_structure_parallel.py
FUCHS/permutate_motifs.py
FUCHS/proportion_of_fully_covered_circRNAs.py
FUCHS/replace_ids_with_names.py
FUCHS/write_fasta_for_fimo.py
FUCHS.egg-info/PKG-INFO
FUCHS.egg-info/SOURCES.txt
FUCHS.egg-info/dependency_links.txt
FUCHS.egg-info/entry_points.txt
FUCHS.egg-info/not-zip-safe
FUCHS.egg-info/requires.txt
FUCHS.egg-info/top_level.txt
data/gold/hek293_A.alternative_splicing.txt
data/gold/hek293_A.exon_counts.bed
data/gold/hek293_A.exon_counts.txt
data/gold/hek293_A.mate_status.txt
data/gold/hek293_A.skipped_exons.bed
data/gold/hek293_A.skipped_exons.txt
data/gold/hek293_B.alternative_splicing.txt
data/gold/hek293_B.exon_counts.bed
data/gold/hek293_B.exon_counts.txt
data/gold/hek293_B.mate_status.txt
data/gold/hek293_B.skipped_exons.bed
data/gold/hek293_B.skipped_exons.txt
data/gold/hek293_A/10_101667886_101676436_5reads.sorted.bam
data/gold/hek293_A/10_101667886_101676436_5reads.sorted.bam.bai
data/gold/hek293_A/10_124940374_124943307_4reads.sorted.bam
data/gold/hek293_A/10_124940374_124943307_4reads.sorted.bam.bai
data/gold/hek293_A/10_124942457_124943307_19reads.sorted.bam
data/gold/hek293_A/10_124942457_124943307_19reads.sorted.bam.bai
data/gold/hek293_A/10_5785142_5800705_9reads.sorted.bam
data/gold/hek293_A/10_5785142_5800705_9reads.sorted.bam.bai
data/gold/hek293_A/10_68468123_68470163_4reads.sorted.bam
data/gold/hek293_A/10_68468123_68470163_4reads.sorted.bam.bai
data/gold/hek293_A/10_7243558_7285954_5reads.sorted.bam
data/gold/hek293_A/10_7243558_7285954_5reads.sorted.bam.bai
data/gold/hek293_A/10_7797047_7802854_7reads.sorted.bam
data/gold/hek293_A/10_7797047_7802854_7reads.sorted.bam.bai
data/gold/hek293_A/10_84371014_84373815_4reads.sorted.bam
data/gold/hek293_A/10_84371014_84373815_4reads.sorted.bam.bai
data/gold/hek293_A/11_103303093_103323990_4reads.sorted.bam
data/gold/hek293_A/11_103303093_103323990_4reads.sorted.bam.bai
