Metadata-Version: 1.2
Name: FUCHS
Version: 0.3.0
Summary: FUll circular RNA CHaracterization from RNA-Seq
Home-page: https://github.com/dieterich-lab/FUCHS
Author: Franzi Metge
Author-email: franziska.metge@age.mpg.de
Maintainer: Tobias Jakobi
Maintainer-email: Tobias.Jakobi@med.Uni-Heidelberg.DE
License: License :: OSI Approved :: GNU General Public License (GPL)
Project-URL: Bug Reports, https://github.com/dieterich-lab/FUCHS/issues
Project-URL: Dieterich Lab, https://dieterichlab.org
Project-URL: Source, https://github.com/dieterich-lab/FUCHS
Project-URL: Documentation, http://docs.circ.tools
Keywords: circular RNA characterization
Platform: UNKNOWN
Classifier: Development Status :: 4 - Beta
Classifier: Intended Audience :: Science/Research
Classifier: Topic :: Scientific/Engineering :: Bio-Informatics
Classifier: License :: OSI Approved :: GNU General Public License (GPL)
Classifier: Programming Language :: Python :: 3.5
Classifier: Programming Language :: Python :: 3.6
Classifier: Programming Language :: Python :: 3.7
Classifier: Programming Language :: Python :: 3.8
